{
  "version": 1,
  "generated": "2025-12-17T09:19:08Z",
  "platforms": {
    "darwin-amd64": {
      "packages": [
        {
          "name": "php8.5-bcmath",
          "version": "8.5.0",
          "revision": 1,
          "description": "PHP 8.5 BCMath arbitrary precision",
          "depends": [
            "php8.5-common (>= 8.5.0)"
          ],
          "provides": [
            "php-bcmath"
          ],
          "url": "https://github.com/phm-dev/php-packages/releases/download/v6/php8.5-bcmath_8.5.0-1_darwin-amd64.tar.gz",
          "sha256": "923063b9e58aaaf47f79b0274d468607c04fd2035d3e2ef9335f20bc49f766cf",
          "size": 358,
          "installed_size": 0
        },
        {
          "name": "php8.5-calendar",
          "version": "8.5.0",
          "revision": 1,
          "description": "PHP 8.5 Calendar functions",
          "depends": [
            "php8.5-common (>= 8.5.0)"
          ],
          "provides": [
            "php-calendar"
          ],
          "url": "https://github.com/phm-dev/php-packages/releases/download/v6/php8.5-calendar_8.5.0-1_darwin-amd64.tar.gz",
          "sha256": "85bd0f869dab6c2cb3188d4b55d542cfd380cffba8f30d84915a4f8854245ec5",
          "size": 349,
          "installed_size": 0
        },
        {
          "name": "php8.5-cgi",
          "version": "8.5.0",
          "revision": 1,
          "description": "PHP 8.5 CGI binary",
          "depends": [
            "php8.5-common (>= 8.5.0)"
          ],
          "provides": [],
          "url": "https://github.com/phm-dev/php-packages/releases/download/v6/php8.5-cgi_8.5.0-1_darwin-amd64.tar.gz",
          "sha256": "77e1a47d7314483e31e62c8e5fc0e60da21ef7763e10970553a39ced19b8f17b",
          "size": 6199611,
          "installed_size": 25993216
        },
        {
          "name": "php8.5-cli",
          "version": "8.5.0",
          "revision": 1,
          "description": "PHP 8.5 CLI interpreter",
          "depends": [
            "php8.5-common (>= 8.5.0)"
          ],
          "provides": [],
          "url": "https://github.com/phm-dev/php-packages/releases/download/v6/php8.5-cli_8.5.0-1_darwin-amd64.tar.gz",
          "sha256": "cba70d7279b9e368e7fd5cdd1e9b7174eab5d2bbb7c1e662ad90dfca99b11b14",
          "size": 6239691,
          "installed_size": 26079232
        },
        {
          "name": "php8.5-common",
          "version": "8.5.0",
          "revision": 1,
          "description": "PHP 8.5 common files",
          "depends": [],
          "provides": [],
          "url": "https://github.com/phm-dev/php-packages/releases/download/v6/php8.5-common_8.5.0-1_darwin-amd64.tar.gz",
          "sha256": "8fbdc444c77dfd638dc380534ade4dda14eb637276993a6c32f36420daa28188",
          "size": 48662,
          "installed_size": 172032
        },
        {
          "name": "php8.5-curl",
          "version": "8.5.0",
          "revision": 1,
          "description": "PHP 8.5 cURL support",
          "depends": [
            "php8.5-common (>= 8.5.0)"
          ],
          "provides": [
            "php-curl"
          ],
          "url": "https://github.com/phm-dev/php-packages/releases/download/v6/php8.5-curl_8.5.0-1_darwin-amd64.tar.gz",
          "sha256": "40fcea0bc6dbf2da3c7d0b8e87209fba9b3904d7fec258a3680791f1d21b7c11",
          "size": 346,
          "installed_size": 0
        },
        {
          "name": "php8.5-dev",
          "version": "8.5.0",
          "revision": 1,
          "description": "PHP 8.5 development files",
          "depends": [
            "php8.5-common (>= 8.5.0)"
          ],
          "provides": [],
          "url": "https://github.com/phm-dev/php-packages/releases/download/v6/php8.5-dev_8.5.0-1_darwin-amd64.tar.gz",
          "sha256": "cf2860fdccf472e8745b852a7d5270b34297954436c045bafdcabe03fbe50b7c",
          "size": 1379877,
          "installed_size": 9605120
        },
        {
          "name": "php8.5-exif",
          "version": "8.5.0",
          "revision": 1,
          "description": "PHP 8.5 EXIF metadata",
          "depends": [
            "php8.5-common (>= 8.5.0)"
          ],
          "provides": [
            "php-exif"
          ],
          "url": "https://github.com/phm-dev/php-packages/releases/download/v6/php8.5-exif_8.5.0-1_darwin-amd64.tar.gz",
          "sha256": "0b6953fbfb2f3e8d611a84ff15fbd09b6f3195541f486b9774326285c09f1b09",
          "size": 349,
          "installed_size": 0
        },
        {
          "name": "php8.5-fpm",
          "version": "8.5.0",
          "revision": 1,
          "description": "PHP 8.5 FPM (FastCGI Process Manager)",
          "depends": [
            "php8.5-common (>= 8.5.0)"
          ],
          "provides": [],
          "url": "https://github.com/phm-dev/php-packages/releases/download/v6/php8.5-fpm_8.5.0-1_darwin-amd64.tar.gz",
          "sha256": "9c8777d81f6e09706be5ae3657042e5a89e3c2e58fe537a3e98ff4c2b9f2dcfe",
          "size": 6253800,
          "installed_size": 26124288
        },
        {
          "name": "php8.5-ftp",
          "version": "8.5.0",
          "revision": 1,
          "description": "PHP 8.5 FTP support",
          "depends": [
            "php8.5-common (>= 8.5.0)"
          ],
          "provides": [
            "php-ftp"
          ],
          "url": "https://github.com/phm-dev/php-packages/releases/download/v6/php8.5-ftp_8.5.0-1_darwin-amd64.tar.gz",
          "sha256": "a7b7a620656d3ded657908ee4b0ab060d4ea5d5edfb199265650b16fe6ca9e11",
          "size": 344,
          "installed_size": 0
        },
        {
          "name": "php8.5-gd",
          "version": "8.5.0",
          "revision": 1,
          "description": "PHP 8.5 GD graphics library",
          "depends": [
            "php8.5-common (>= 8.5.0)"
          ],
          "provides": [
            "php-gd"
          ],
          "url": "https://github.com/phm-dev/php-packages/releases/download/v6/php8.5-gd_8.5.0-1_darwin-amd64.tar.gz",
          "sha256": "1d791c42cea729967aa4c136c910cc2ff9e9624ef3cdcd9ac2a6d4f42f57cd8e",
          "size": 351,
          "installed_size": 0
        },
        {
          "name": "php8.5-intl",
          "version": "8.5.0",
          "revision": 1,
          "description": "PHP 8.5 Internationalization support",
          "depends": [
            "php8.5-common (>= 8.5.0)"
          ],
          "provides": [
            "php-intl"
          ],
          "url": "https://github.com/phm-dev/php-packages/releases/download/v6/php8.5-intl_8.5.0-1_darwin-amd64.tar.gz",
          "sha256": "7d8762a2885d2e41a3a5f12e2697635846056c06c4184e01c01476f11f14703c",
          "size": 353,
          "installed_size": 0
        },
        {
          "name": "php8.5-mbstring",
          "version": "8.5.0",
          "revision": 1,
          "description": "PHP 8.5 Multibyte string support",
          "depends": [
            "php8.5-common (>= 8.5.0)"
          ],
          "provides": [
            "php-mbstring"
          ],
          "url": "https://github.com/phm-dev/php-packages/releases/download/v6/php8.5-mbstring_8.5.0-1_darwin-amd64.tar.gz",
          "sha256": "8d8cb094eb126072d03dfc4771891dad2e439f0b4a0107db840213a1a0c8f02a",
          "size": 355,
          "installed_size": 0
        },
        {
          "name": "php8.5-mysql",
          "version": "8.5.0",
          "revision": 1,
          "description": "PHP 8.5 MySQL support (mysqli, pdo_mysql)",
          "depends": [
            "php8.5-common (>= 8.5.0)"
          ],
          "provides": [
            "php-mysql"
          ],
          "url": "https://github.com/phm-dev/php-packages/releases/download/v6/php8.5-mysql_8.5.0-1_darwin-amd64.tar.gz",
          "sha256": "381872e390c0c9b97573e41dc7cb1957d951abff45a1a797f5999076bb98ba61",
          "size": 361,
          "installed_size": 0
        },
        {
          "name": "php8.5-opcache",
          "version": "8.5.0",
          "revision": 1,
          "description": "PHP 8.5 OPcache configuration (built into PHP 8.5+)",
          "depends": [
            "php8.5-common (>= 8.5.0)"
          ],
          "provides": [],
          "url": "https://github.com/phm-dev/php-packages/releases/download/v6/php8.5-opcache_8.5.0-1_darwin-amd64.tar.gz",
          "sha256": "16cb5878bcb82ee16889c6c6d223b9f1713f336251571e07405e7ec5ff6183d2",
          "size": 657,
          "installed_size": 4096
        },
        {
          "name": "php8.5-pcntl",
          "version": "8.5.0",
          "revision": 1,
          "description": "PHP 8.5 Process control",
          "depends": [
            "php8.5-common (>= 8.5.0)"
          ],
          "provides": [
            "php-pcntl"
          ],
          "url": "https://github.com/phm-dev/php-packages/releases/download/v6/php8.5-pcntl_8.5.0-1_darwin-amd64.tar.gz",
          "sha256": "d3a04c5e77df799e75f4dfed44675b68a2a47b007adf29c89dfd1f7cc3d6c94c",
          "size": 348,
          "installed_size": 0
        },
        {
          "name": "php8.5-pear",
          "version": "8.5.0",
          "revision": 1,
          "description": "PHP 8.5 PEAR/PECL package manager",
          "depends": [
            "php8.5-cli (>= 8.5.0)"
          ],
          "provides": [],
          "url": "https://github.com/phm-dev/php-packages/releases/download/v6/php8.5-pear_8.5.0-1_darwin-amd64.tar.gz",
          "sha256": "5e313fd298940e861a5063139ee816d2c7a74dd22130ac7609b25d05412cf8e4",
          "size": 344785,
          "installed_size": 2244608
        },
        {
          "name": "php8.5-pgsql",
          "version": "8.5.0",
          "revision": 1,
          "description": "PHP 8.5 PostgreSQL support",
          "depends": [
            "php8.5-common (>= 8.5.0)"
          ],
          "provides": [
            "php-pgsql"
          ],
          "url": "https://github.com/phm-dev/php-packages/releases/download/v6/php8.5-pgsql_8.5.0-1_darwin-amd64.tar.gz",
          "sha256": "998be568367e700018907999c7f3a9bcd6b338180300cb48e8e4909d934a026b",
          "size": 352,
          "installed_size": 0
        },
        {
          "name": "php8.5-readline",
          "version": "8.5.0",
          "revision": 1,
          "description": "PHP 8.5 Readline support",
          "depends": [
            "php8.5-common (>= 8.5.0)"
          ],
          "provides": [
            "php-readline"
          ],
          "url": "https://github.com/phm-dev/php-packages/releases/download/v6/php8.5-readline_8.5.0-1_darwin-amd64.tar.gz",
          "sha256": "0832f6c0527ba3eef6faf6db1713e5fe2f3e87be68296f79005d36e3b4301ef8",
          "size": 349,
          "installed_size": 0
        },
        {
          "name": "php8.5-soap",
          "version": "8.5.0",
          "revision": 1,
          "description": "PHP 8.5 SOAP support",
          "depends": [
            "php8.5-common (>= 8.5.0)"
          ],
          "provides": [
            "php-soap"
          ],
          "url": "https://github.com/phm-dev/php-packages/releases/download/v6/php8.5-soap_8.5.0-1_darwin-amd64.tar.gz",
          "sha256": "1224a5df0ffba012f08ad2811dd730b86504714b6dc372511ac4f58ea685613c",
          "size": 347,
          "installed_size": 0
        },
        {
          "name": "php8.5-sockets",
          "version": "8.5.0",
          "revision": 1,
          "description": "PHP 8.5 Socket support",
          "depends": [
            "php8.5-common (>= 8.5.0)"
          ],
          "provides": [
            "php-sockets"
          ],
          "url": "https://github.com/phm-dev/php-packages/releases/download/v6/php8.5-sockets_8.5.0-1_darwin-amd64.tar.gz",
          "sha256": "4d9d163d670ac7c76e0993a4e9c928e4d4a137c811e11cfdc88fbd7b8253aadd",
          "size": 348,
          "installed_size": 0
        },
        {
          "name": "php8.5-sqlite3",
          "version": "8.5.0",
          "revision": 1,
          "description": "PHP 8.5 SQLite3 support",
          "depends": [
            "php8.5-common (>= 8.5.0)"
          ],
          "provides": [
            "php-sqlite3"
          ],
          "url": "https://github.com/phm-dev/php-packages/releases/download/v6/php8.5-sqlite3_8.5.0-1_darwin-amd64.tar.gz",
          "sha256": "85cb64957013d61ae5ff6dccaf504d9b94d3b1734d58d44722a9f3af57028c33",
          "size": 350,
          "installed_size": 0
        },
        {
          "name": "php8.5-xml",
          "version": "8.5.0",
          "revision": 1,
          "description": "PHP 8.5 XML support",
          "depends": [
            "php8.5-common (>= 8.5.0)"
          ],
          "provides": [
            "php-xml"
          ],
          "url": "https://github.com/phm-dev/php-packages/releases/download/v6/php8.5-xml_8.5.0-1_darwin-amd64.tar.gz",
          "sha256": "ca559509a5cc61db28c0f07136c9646f6de68c9ad2c83c142a1663e00a8ea149",
          "size": 346,
          "installed_size": 0
        },
        {
          "name": "php8.5-zip",
          "version": "8.5.0",
          "revision": 1,
          "description": "PHP 8.5 ZIP support",
          "depends": [
            "php8.5-common (>= 8.5.0)"
          ],
          "provides": [
            "php-zip"
          ],
          "url": "https://github.com/phm-dev/php-packages/releases/download/v6/php8.5-zip_8.5.0-1_darwin-amd64.tar.gz",
          "sha256": "7b3ff9c813e656658f5de9098ede31f74e3423a773c51bf77034ac6d815719ed",
          "size": 345,
          "installed_size": 0
        },
        {
          "name": "php8.5",
          "version": "8.5.0",
          "revision": 1,
          "description": "PHP 8.5 meta-package (CLI + common)",
          "depends": [
            "php8.5-cli (>= 8.5.0)",
            "php8.5-common (>= 8.5.0)"
          ],
          "provides": [
            "php"
          ],
          "url": "https://github.com/phm-dev/php-packages/releases/download/v6/php8.5_8.5.0-1_darwin-amd64.tar.gz",
          "sha256": "ff65b59165880d2ad72c9b0faaa450f1d6b55e94c680bfb5ace3bc387c42c6ee",
          "size": 358,
          "installed_size": 0
        }
      ]
    },
    "darwin-arm64": {
      "packages": [
        {
          "name": "php8.5-bcmath",
          "version": "8.5.0",
          "revision": 1,
          "description": "PHP 8.5 BCMath arbitrary precision",
          "depends": [
            "php8.5-common (>= 8.5.0)"
          ],
          "provides": [
            "php-bcmath"
          ],
          "url": "https://github.com/phm-dev/php-packages/releases/download/v6/php8.5-bcmath_8.5.0-1_darwin-arm64.tar.gz",
          "sha256": "1c70adc223b1680b42ebb149e339a378d3f28a898ed594af4a35e80541ead21f",
          "size": 357,
          "installed_size": 0
        },
        {
          "name": "php8.5-calendar",
          "version": "8.5.0",
          "revision": 1,
          "description": "PHP 8.5 Calendar functions",
          "depends": [
            "php8.5-common (>= 8.5.0)"
          ],
          "provides": [
            "php-calendar"
          ],
          "url": "https://github.com/phm-dev/php-packages/releases/download/v6/php8.5-calendar_8.5.0-1_darwin-arm64.tar.gz",
          "sha256": "874541581ca70aa155ab00901e5b55999166cb7b87b326db886a441f390298da",
          "size": 349,
          "installed_size": 0
        },
        {
          "name": "php8.5-cgi",
          "version": "8.5.0",
          "revision": 1,
          "description": "PHP 8.5 CGI binary",
          "depends": [
            "php8.5-common (>= 8.5.0)"
          ],
          "provides": [],
          "url": "https://github.com/phm-dev/php-packages/releases/download/v6/php8.5-cgi_8.5.0-1_darwin-arm64.tar.gz",
          "sha256": "bdb000e497499a6f483c1d9412ef5f9f21804923a98ae68f0b757bffab52e555",
          "size": 6104907,
          "installed_size": 25767936
        },
        {
          "name": "php8.5-cli",
          "version": "8.5.0",
          "revision": 1,
          "description": "PHP 8.5 CLI interpreter",
          "depends": [
            "php8.5-common (>= 8.5.0)"
          ],
          "provides": [],
          "url": "https://github.com/phm-dev/php-packages/releases/download/v6/php8.5-cli_8.5.0-1_darwin-arm64.tar.gz",
          "sha256": "a67e7e9c64a7ab1ba4d8297232c1d2903f7430db5d58ac23d3357e1c5b04ac54",
          "size": 6145608,
          "installed_size": 25849856
        },
        {
          "name": "php8.5-common",
          "version": "8.5.0",
          "revision": 1,
          "description": "PHP 8.5 common files",
          "depends": [],
          "provides": [],
          "url": "https://github.com/phm-dev/php-packages/releases/download/v6/php8.5-common_8.5.0-1_darwin-arm64.tar.gz",
          "sha256": "c34a11bb344403555aa9794848b4f4f85c67b2fec912906088cc83ea4366be15",
          "size": 48662,
          "installed_size": 172032
        },
        {
          "name": "php8.5-curl",
          "version": "8.5.0",
          "revision": 1,
          "description": "PHP 8.5 cURL support",
          "depends": [
            "php8.5-common (>= 8.5.0)"
          ],
          "provides": [
            "php-curl"
          ],
          "url": "https://github.com/phm-dev/php-packages/releases/download/v6/php8.5-curl_8.5.0-1_darwin-arm64.tar.gz",
          "sha256": "19bef1e83ebea0bb0426d626e92c036e38fb52f4502c1bcc5724398ae06b5b10",
          "size": 346,
          "installed_size": 0
        },
        {
          "name": "php8.5-dev",
          "version": "8.5.0",
          "revision": 1,
          "description": "PHP 8.5 development files",
          "depends": [
            "php8.5-common (>= 8.5.0)"
          ],
          "provides": [],
          "url": "https://github.com/phm-dev/php-packages/releases/download/v6/php8.5-dev_8.5.0-1_darwin-arm64.tar.gz",
          "sha256": "ad0e64b1870723f734bd30a38758a5a4b4b3d096e85f12ecb30614ca6b803792",
          "size": 1379974,
          "installed_size": 9605120
        },
        {
          "name": "php8.5-exif",
          "version": "8.5.0",
          "revision": 1,
          "description": "PHP 8.5 EXIF metadata",
          "depends": [
            "php8.5-common (>= 8.5.0)"
          ],
          "provides": [
            "php-exif"
          ],
          "url": "https://github.com/phm-dev/php-packages/releases/download/v6/php8.5-exif_8.5.0-1_darwin-arm64.tar.gz",
          "sha256": "52976b11718175d5a5d38e993e643eebe4a0461ac1e0449116b0640df45c5b85",
          "size": 349,
          "installed_size": 0
        },
        {
          "name": "php8.5-fpm",
          "version": "8.5.0",
          "revision": 1,
          "description": "PHP 8.5 FPM (FastCGI Process Manager)",
          "depends": [
            "php8.5-common (>= 8.5.0)"
          ],
          "provides": [],
          "url": "https://github.com/phm-dev/php-packages/releases/download/v6/php8.5-fpm_8.5.0-1_darwin-arm64.tar.gz",
          "sha256": "0b0acf60c030de1a4a3edb2d7c647f424022950c396865f818d00978d146b3bb",
          "size": 6157187,
          "installed_size": 25899008
        },
        {
          "name": "php8.5-ftp",
          "version": "8.5.0",
          "revision": 1,
          "description": "PHP 8.5 FTP support",
          "depends": [
            "php8.5-common (>= 8.5.0)"
          ],
          "provides": [
            "php-ftp"
          ],
          "url": "https://github.com/phm-dev/php-packages/releases/download/v6/php8.5-ftp_8.5.0-1_darwin-arm64.tar.gz",
          "sha256": "ac5868b3fde2fecc41b8e659c7e1373af4cc0090d2479d830ecc980a98aa688b",
          "size": 344,
          "installed_size": 0
        },
        {
          "name": "php8.5-gd",
          "version": "8.5.0",
          "revision": 1,
          "description": "PHP 8.5 GD graphics library",
          "depends": [
            "php8.5-common (>= 8.5.0)"
          ],
          "provides": [
            "php-gd"
          ],
          "url": "https://github.com/phm-dev/php-packages/releases/download/v6/php8.5-gd_8.5.0-1_darwin-arm64.tar.gz",
          "sha256": "59b1e37df3a743d3fc060096bac9518fdb3e0569a6d16c7de009b510e56fedd4",
          "size": 352,
          "installed_size": 0
        },
        {
          "name": "php8.5-intl",
          "version": "8.5.0",
          "revision": 1,
          "description": "PHP 8.5 Internationalization support",
          "depends": [
            "php8.5-common (>= 8.5.0)"
          ],
          "provides": [
            "php-intl"
          ],
          "url": "https://github.com/phm-dev/php-packages/releases/download/v6/php8.5-intl_8.5.0-1_darwin-arm64.tar.gz",
          "sha256": "a09ae10d32c32b4531c0763fb8e8dd46faab560816241096a4a83bfdd1ad3675",
          "size": 353,
          "installed_size": 0
        },
        {
          "name": "php8.5-mbstring",
          "version": "8.5.0",
          "revision": 1,
          "description": "PHP 8.5 Multibyte string support",
          "depends": [
            "php8.5-common (>= 8.5.0)"
          ],
          "provides": [
            "php-mbstring"
          ],
          "url": "https://github.com/phm-dev/php-packages/releases/download/v6/php8.5-mbstring_8.5.0-1_darwin-arm64.tar.gz",
          "sha256": "960b97e974c35fc59943912e774724ad3b25c2601d84f232fc97c9768d63f6a6",
          "size": 356,
          "installed_size": 0
        },
        {
          "name": "php8.5-mysql",
          "version": "8.5.0",
          "revision": 1,
          "description": "PHP 8.5 MySQL support (mysqli, pdo_mysql)",
          "depends": [
            "php8.5-common (>= 8.5.0)"
          ],
          "provides": [
            "php-mysql"
          ],
          "url": "https://github.com/phm-dev/php-packages/releases/download/v6/php8.5-mysql_8.5.0-1_darwin-arm64.tar.gz",
          "sha256": "06d75e051e1cfc297eb3b6f2ff93d9e6a5880a5c6a61b6797680a1ec9932171b",
          "size": 361,
          "installed_size": 0
        },
        {
          "name": "php8.5-opcache",
          "version": "8.5.0",
          "revision": 1,
          "description": "PHP 8.5 OPcache configuration (built into PHP 8.5+)",
          "depends": [
            "php8.5-common (>= 8.5.0)"
          ],
          "provides": [],
          "url": "https://github.com/phm-dev/php-packages/releases/download/v6/php8.5-opcache_8.5.0-1_darwin-arm64.tar.gz",
          "sha256": "cdc916b8382fd6ad33271fb9712d1e910879732268b899e07af91ea0768c7cad",
          "size": 657,
          "installed_size": 4096
        },
        {
          "name": "php8.5-pcntl",
          "version": "8.5.0",
          "revision": 1,
          "description": "PHP 8.5 Process control",
          "depends": [
            "php8.5-common (>= 8.5.0)"
          ],
          "provides": [
            "php-pcntl"
          ],
          "url": "https://github.com/phm-dev/php-packages/releases/download/v6/php8.5-pcntl_8.5.0-1_darwin-arm64.tar.gz",
          "sha256": "47a664df1e1111bac946603175ff7c4e9fa9c5a086a86f3caf4584e171034a31",
          "size": 348,
          "installed_size": 0
        },
        {
          "name": "php8.5-pear",
          "version": "8.5.0",
          "revision": 1,
          "description": "PHP 8.5 PEAR/PECL package manager",
          "depends": [
            "php8.5-cli (>= 8.5.0)"
          ],
          "provides": [],
          "url": "https://github.com/phm-dev/php-packages/releases/download/v6/php8.5-pear_8.5.0-1_darwin-arm64.tar.gz",
          "sha256": "135382c666756216336cda1b5f75f56c9c4b14409bb0c8e99a7ab2c9a78dfc32",
          "size": 344755,
          "installed_size": 2244608
        },
        {
          "name": "php8.5-pgsql",
          "version": "8.5.0",
          "revision": 1,
          "description": "PHP 8.5 PostgreSQL support",
          "depends": [
            "php8.5-common (>= 8.5.0)"
          ],
          "provides": [
            "php-pgsql"
          ],
          "url": "https://github.com/phm-dev/php-packages/releases/download/v6/php8.5-pgsql_8.5.0-1_darwin-arm64.tar.gz",
          "sha256": "dcd4270f92fd0dcc9cc3d0d159999f36fac232e78ba698ed504b1713b191650a",
          "size": 352,
          "installed_size": 0
        },
        {
          "name": "php8.5-readline",
          "version": "8.5.0",
          "revision": 1,
          "description": "PHP 8.5 Readline support",
          "depends": [
            "php8.5-common (>= 8.5.0)"
          ],
          "provides": [
            "php-readline"
          ],
          "url": "https://github.com/phm-dev/php-packages/releases/download/v6/php8.5-readline_8.5.0-1_darwin-arm64.tar.gz",
          "sha256": "75afaf9bb15790fbbd032c9ca2c1550f452a896dd071c1d35605f5444dd580c3",
          "size": 348,
          "installed_size": 0
        },
        {
          "name": "php8.5-soap",
          "version": "8.5.0",
          "revision": 1,
          "description": "PHP 8.5 SOAP support",
          "depends": [
            "php8.5-common (>= 8.5.0)"
          ],
          "provides": [
            "php-soap"
          ],
          "url": "https://github.com/phm-dev/php-packages/releases/download/v6/php8.5-soap_8.5.0-1_darwin-arm64.tar.gz",
          "sha256": "40cf86aa21ea8803fd91b34ae9dd13e3a9745918710b3e1478c5a4fef97a5698",
          "size": 347,
          "installed_size": 0
        },
        {
          "name": "php8.5-sockets",
          "version": "8.5.0",
          "revision": 1,
          "description": "PHP 8.5 Socket support",
          "depends": [
            "php8.5-common (>= 8.5.0)"
          ],
          "provides": [
            "php-sockets"
          ],
          "url": "https://github.com/phm-dev/php-packages/releases/download/v6/php8.5-sockets_8.5.0-1_darwin-arm64.tar.gz",
          "sha256": "0f1e8e56557e090f4ca3eb51de0936eb7fc39b0a62f691d6e51f4a399def6a1d",
          "size": 350,
          "installed_size": 0
        },
        {
          "name": "php8.5-sqlite3",
          "version": "8.5.0",
          "revision": 1,
          "description": "PHP 8.5 SQLite3 support",
          "depends": [
            "php8.5-common (>= 8.5.0)"
          ],
          "provides": [
            "php-sqlite3"
          ],
          "url": "https://github.com/phm-dev/php-packages/releases/download/v6/php8.5-sqlite3_8.5.0-1_darwin-arm64.tar.gz",
          "sha256": "1626c50a6645a904017fd36af7d1540e4203c378b78a4ad533441a7e9cfe555c",
          "size": 351,
          "installed_size": 0
        },
        {
          "name": "php8.5-xml",
          "version": "8.5.0",
          "revision": 1,
          "description": "PHP 8.5 XML support",
          "depends": [
            "php8.5-common (>= 8.5.0)"
          ],
          "provides": [
            "php-xml"
          ],
          "url": "https://github.com/phm-dev/php-packages/releases/download/v6/php8.5-xml_8.5.0-1_darwin-arm64.tar.gz",
          "sha256": "78ffe68fbd60de069780822b733af2ad87270946cea58991d01776e3446ee98d",
          "size": 346,
          "installed_size": 0
        },
        {
          "name": "php8.5-zip",
          "version": "8.5.0",
          "revision": 1,
          "description": "PHP 8.5 ZIP support",
          "depends": [
            "php8.5-common (>= 8.5.0)"
          ],
          "provides": [
            "php-zip"
          ],
          "url": "https://github.com/phm-dev/php-packages/releases/download/v6/php8.5-zip_8.5.0-1_darwin-arm64.tar.gz",
          "sha256": "2c5734c0a117b0cee8768784e5b37cb264b37bbf4323e979eaeb8ce95cca652f",
          "size": 345,
          "installed_size": 0
        },
        {
          "name": "php8.5",
          "version": "8.5.0",
          "revision": 1,
          "description": "PHP 8.5 meta-package (CLI + common)",
          "depends": [
            "php8.5-cli (>= 8.5.0)",
            "php8.5-common (>= 8.5.0)"
          ],
          "provides": [
            "php"
          ],
          "url": "https://github.com/phm-dev/php-packages/releases/download/v6/php8.5_8.5.0-1_darwin-arm64.tar.gz",
          "sha256": "59efe365f4dd500ce54002f171b0acc82d599a6235f4f7e264389d7d1710627f",
          "size": 358,
          "installed_size": 0
        }
      ]
    }
  }
}
